MANIFEST.in
README.md
requirements.txt
setup.py
cfmonitor/__init__.py
cfmonitor/example.py
cfmonitor/space.py
cfspacemonitor.egg-info/PKG-INFO
cfspacemonitor.egg-info/SOURCES.txt
cfspacemonitor.egg-info/dependency_links.txt
cfspacemonitor.egg-info/requires.txt
cfspacemonitor.egg-info/top_level.txt
test/test_cfmonitorspace.py