Metadata-Version: 1.0
Name: cfspacemonitor
Version: 0.0.2
Summary: Cloud Foundry Space Monitor
Home-page: https://github.com/hsdp/cf-space-monitor
Author: Adam Jaso
Author-email: ajaso@hsdp.io
License: Apache License Version 2.0
Platform: UNKNOWN
